pythum/__init__.py
pythum/engine.py
pythum/qubit.py
pythum/qublock.py
pythum-0.1.1.dist-info/LICENSE
pythum-0.1.1.dist-info/METADATA
pythum-0.1.1.dist-info/WHEEL
pythum-0.1.1.dist-info/top_level.txt
pythum-0.1.1.dist-info/RECORD
