Metadata-Version: 2.1
Name: pythum
Version: 0.1.1
Summary: Simple minimalist quantum computing simalation for python
Home-page: https://github.com/metadeta96/pythum
Author: metadeta96
Author-email: metadeta96@gmail.com
License: UNKNOWN
Download-URL: https://github.com/metadeta96/pythum
Keywords: quantum,python,pythum,computing,simulator,simulation
Platform: UNKNOWN
Classifier: Programming Language :: Python :: 3
Classifier: License :: OSI Approved :: MIT License
Classifier: Operating System :: OS Independent
